cudatalog/__init__.py
cudatalog-0.0.0.dist-info/METADATA
cudatalog-0.0.0.dist-info/WHEEL
cudatalog-0.0.0.dist-info/top_level.txt
cudatalog-0.0.0.dist-info/RECORD
