Metadata-Version: 2.4
Name: cudatalog
Version: 0.0.0
Summary: Datalog Engine written in CUDA
Author-email: SowmithK <sowmith1729@gmail.com>
